INLD/INLD.py
INLD/__init__.py
INLD/lang_detect.model
INLD/vectorizer.vect
INLD-0.0.3.data/data/LICENSE
INLD-0.0.3.data/data/lang_detect.model
INLD-0.0.3.data/data/vectorizer.vect
INLD-0.0.3.dist-info/LICENSE
INLD-0.0.3.dist-info/METADATA
INLD-0.0.3.dist-info/WHEEL
INLD-0.0.3.dist-info/top_level.txt
INLD-0.0.3.dist-info/RECORD
