Metadata-Version: 2.1
Name: INLD
Version: 0.0.3
Summary: A package to detect Indian natural languages
Home-page: https://github.com/jagman32/INLD
Author: Jagmanjot
Author-email: jagmanjotsingh.becse17@pec.edu.in
License: UNKNOWN
Platform: UNKNOWN
Classifier: Programming Language :: Python :: 3
Classifier: License :: OSI Approved :: MIT License
Classifier: Operating System :: OS Independent
Requires-Python: >=3.6
